[
  {
    "id": "eridan1",
    "x": 2800,
    "y": 700,
    "radius": 40,
    "color": "#66ffd9",
    "borderColor": null,
    "name": "Alfa Eridania",
    "info": "",
    "visible": true,
    "unknown" : false,
    "race": "Eridan"
  },
  {
    "id": "eridan2",
    "x": 3040,
    "y": 860,
    "radius": 30,
    "color": "#7b816c",
    "borderColor": null,
    "name": "Beta Eridania",
    "info": "",
    "visible": true,
    "unknown" : false,
    "race": "Eridan"
  },
  {
    "id": "eridan2-a",
    "x": 3088,
    "y": 848,
    "radius": 10,
    "color": "#a4d331",
    "borderColor": null,
    "name": "Memorial",
    "info": "",
    "visible": true,
    "unknown" : false,
    "race": "Eridan"
  },
  {
    "id": "eridan3",
    "x": 2640,
    "y": 1131,
    "radius": 46,
    "color": "#7b816c",
    "borderColor": null,
    "name": "Gama Eridania",
    "info": "",
    "visible": true,
    "unknown" : false,
    "race": "Eridan"
  },
  {
    "id": "eridan4",
    "x": 3200,
    "y": 2000,
    "radius": 46,
    "color": "#1eb2c7",
    "borderColor": null,
    "name": "Delta Eridania",
    "info": "",
    "visible": true,
    "unknown" : false,
    "race": "Eridan"
  },
  {
    "id": "eirenarchis",
    "x": 3500,
    "y": 1600,
    "radius": 18,
    "color": "#acc9d6",
    "borderColor": null,
    "name": "Eirenarchis",
    "info": "",
    "visible": true,
    "unknown" : false,
    "race": "Eridan"
  },
  {
    "id": "anki",
    "x": 300,
    "y": 400,
    "radius": 22,
    "color": "#FF4500",
    "borderColor": null,
    "name": "Anki",
    "info": "",
    "visible": true,
    "unknown" : true,
    "race": ""
  }
]
